py_pinyin_split/__about__.py
py_pinyin_split/__init__.py
py_pinyin_split/py.typed
py_pinyin_split-5.0.0.dist-info/METADATA
py_pinyin_split-5.0.0.dist-info/WHEEL
py_pinyin_split-5.0.0.dist-info/licenses/LICENSE.txt
py_pinyin_split-5.0.0.dist-info/RECORD
