Metadata-Version: 2.3
Name: py-pinyin-split
Version: 5.0.0
Summary: Library for splitting Hanyu Pinyin phrases into all valid syllable combinations
Project-URL: Documentation, https://github.com/lstrobel/py-pinyin-split#readme
Project-URL: Issues, https://github.com/lstrobel/py-pinyin-split/issues
Project-URL: Source, https://github.com/lstrobel/py-pinyin-split
Author-email: lstrobel <mail@lstrobel.com>, Thomas Lee <thomaslee@throput.com>
Maintainer-email: lstrobel <mail@lstrobel.com>
License: MIT
Keywords: chinese,pinyin
Classifier: Development Status :: 5 - Production/Stable
Classifier: Intended Audience :: Developers
Classifier: License :: OSI Approved :: MIT License
Classifier: Operating System :: OS Independent
Classifier: Programming Language :: Python
Classifier: Programming Language :: Python :: 3.8
Classifier: Programming Language :: Python :: 3.9
Classifier: Programming Language :: Python :: 3.10
Classifier: Programming Language :: Python :: 3.11
Classifier: Programming Language :: Python :: 3.12
Classifier: Programming Language :: Python :: Implementation :: CPython
Classifier: Programming Language :: Python :: Implementation :: PyPy
Classifier: Topic :: Text Processing :: Linguistic
Classifier: Topic :: Utilities
Requires-Python: <3.13,>=3.8
Requires-Dist: marisa-trie>=1.2.1
Requires-Dist: nltk==3.9.1
